{
    "openapi": "3.0.0",
    "info": {
        "title": "API - Autores e Livros",
        "description": "Documentação da API do desafio (Laravel + Sanctum).",
        "version": "1.0.0"
    },
    "servers": [
        {
            "url": "http://localhost:8000/api",
            "description": "Servidor local"
        }
    ],
    "paths": {
        "/auth/register": {
            "post": {
                "tags": [
                    "Auth"
                ],
                "summary": "Registrar um novo usuário",
                "description": "Cria um usuário na API e retorna seus dados.",
                "operationId": "08136088c4862c313b35d6518bab8d3a",
                "requestBody": {
                    "required": true,
                    "content": {
                        "application/json": {
                            "schema": {
                                "required": [
                                    "name",
                                    "email",
                                    "password",
                                    "password_confirmation"
                                ],
                                "properties": {
                                    "name": {
                                        "type": "string",
                                        "example": "Luiz Paulo"
                                    },
                                    "email": {
                                        "type": "string",
                                        "format": "email",
                                        "example": "luiz@example.com"
                                    },
                                    "password": {
                                        "type": "string",
                                        "format": "password",
                                        "example": "senha123"
                                    },
                                    "password_confirmation": {
                                        "type": "string",
                                        "format": "password",
                                        "example": "senha123"
                                    }
                                },
                                "type": "object"
                            }
                        }
                    }
                },
                "responses": {
                    "201": {
                        "description": "Usuário criado com sucesso",
                        "content": {
                            "application/json": {
                                "schema": {
                                    "properties": {
                                        "id": {
                                            "type": "integer",
                                            "example": 1
                                        },
                                        "name": {
                                            "type": "string",
                                            "example": "Luiz Paulo"
                                        },
                                        "email": {
                                            "type": "string",
                                            "example": "luiz@example.com"
                                        }
                                    },
                                    "type": "object"
                                }
                            }
                        }
                    },
                    "422": {
                        "description": "Erros de validação"
                    }
                }
            }
        },
        "/auth/login": {
            "post": {
                "tags": [
                    "Auth"
                ],
                "summary": "Login de usuário",
                "description": "Autentica o usuário e retorna um token de acesso (Bearer).",
                "operationId": "99d66635c4992aeaa6aa44ff653d0563",
                "requestBody": {
                    "required": true,
                    "content": {
                        "application/json": {
                            "schema": {
                                "required": [
                                    "email",
                                    "password"
                                ],
                                "properties": {
                                    "email": {
                                        "type": "string",
                                        "format": "email",
                                        "example": "luiz@example.com"
                                    },
                                    "password": {
                                        "type": "string",
                                        "format": "password",
                                        "example": "senha123"
                                    }
                                },
                                "type": "object"
                            }
                        }
                    }
                },
                "responses": {
                    "200": {
                        "description": "Login realizado com sucesso",
                        "content": {
                            "application/json": {
                                "schema": {
                                    "properties": {
                                        "access_token": {
                                            "type": "string",
                                            "example": "1|abcdefg123456"
                                        },
                                        "token_type": {
                                            "type": "string",
                                            "example": "Bearer"
                                        },
                                        "user": {
                                            "properties": {
                                                "id": {
                                                    "type": "integer",
                                                    "example": 1
                                                },
                                                "name": {
                                                    "type": "string",
                                                    "example": "Luiz Paulo"
                                                },
                                                "email": {
                                                    "type": "string",
                                                    "example": "luiz@example.com"
                                                }
                                            },
                                            "type": "object"
                                        }
                                    },
                                    "type": "object"
                                }
                            }
                        }
                    },
                    "401": {
                        "description": "Usuário ou senha inválidos"
                    },
                    "422": {
                        "description": "Erros de validação"
                    }
                }
            }
        },
        "/auth/logout": {
            "post": {
                "tags": [
                    "Auth"
                ],
                "summary": "Logout",
                "description": "Revoga o token de acesso atual.",
                "operationId": "6abf3b64a4bc7838d56346f05a5153af",
                "responses": {
                    "200": {
                        "description": "Logout realizado com sucesso",
                        "content": {
                            "application/json": {
                                "schema": {
                                    "properties": {
                                        "message": {
                                            "type": "string",
                                            "example": "Logged out"
                                        }
                                    },
                                    "type": "object"
                                }
                            }
                        }
                    },
                    "401": {
                        "description": "Não autenticado"
                    }
                },
                "security": [
                    {
                        "sanctum": []
                    }
                ]
            }
        },
        "/auth/forgot-password": {
            "post": {
                "tags": [
                    "Auth"
                ],
                "summary": "Esqueci minha senha",
                "description": "Gera um link de redefinição de senha e envia para o e-mail informado.",
                "operationId": "fea89d2766defe4ad877001920e3f289",
                "requestBody": {
                    "required": true,
                    "content": {
                        "application/json": {
                            "schema": {
                                "required": [
                                    "email"
                                ],
                                "properties": {
                                    "email": {
                                        "type": "string",
                                        "format": "email",
                                        "example": "luiz@example.com"
                                    }
                                },
                                "type": "object"
                            }
                        }
                    }
                },
                "responses": {
                    "200": {
                        "description": "Status do envio do link de redefinição de senha",
                        "content": {
                            "application/json": {
                                "schema": {
                                    "properties": {
                                        "message": {
                                            "type": "string",
                                            "example": "We have emailed your password reset link."
                                        }
                                    },
                                    "type": "object"
                                }
                            }
                        }
                    },
                    "422": {
                        "description": "Erros de validação"
                    }
                }
            }
        },
        "/authors": {
            "get": {
                "tags": [
                    "Authors"
                ],
                "summary": "Listar autores",
                "operationId": "03597029db468f4b49ca68861b2118e2",
                "parameters": [
                    {
                        "name": "per_page",
                        "in": "query",
                        "description": "Quantidade por página",
                        "required": false,
                        "schema": {
                            "type": "integer",
                            "default": 10
                        }
                    }
                ],
                "responses": {
                    "200": {
                        "description": "Lista paginada de autores"
                    }
                },
                "security": [
                    {
                        "bearerAuth": []
                    }
                ]
            },
            "post": {
                "tags": [
                    "Authors"
                ],
                "summary": "Criar autor",
                "operationId": "c58fcfa1a2e042011ee26b57a00e5c2d",
                "requestBody": {
                    "required": true,
                    "content": {
                        "application/json": {
                            "schema": {
                                "required": [
                                    "name"
                                ],
                                "properties": {
                                    "name": {
                                        "type": "string",
                                        "example": "Robert C. Martin"
                                    },
                                    "bio": {
                                        "type": "string",
                                        "example": "Autor de Clean Code"
                                    }
                                },
                                "type": "object"
                            }
                        }
                    }
                },
                "responses": {
                    "201": {
                        "description": "Autor criado com sucesso"
                    },
                    "422": {
                        "description": "Erro de validação"
                    }
                },
                "security": [
                    {
                        "bearerAuth": []
                    }
                ]
            }
        },
        "/authors/{id}": {
            "get": {
                "tags": [
                    "Authors"
                ],
                "summary": "Mostrar autor",
                "operationId": "a62a46735167db4ec6f25578c0f2ac9c",
                "parameters": [
                    {
                        "name": "id",
                        "in": "path",
                        "description": "ID do autor",
                        "required": true,
                        "schema": {
                            "type": "integer"
                        }
                    }
                ],
                "responses": {
                    "200": {
                        "description": "Autor encontrado"
                    },
                    "404": {
                        "description": "Autor não encontrado"
                    }
                },
                "security": [
                    {
                        "bearerAuth": []
                    }
                ]
            },
            "put": {
                "tags": [
                    "Authors"
                ],
                "summary": "Atualizar autor",
                "operationId": "cf8036fbfd84449d9905eb70a2d63510",
                "parameters": [
                    {
                        "name": "id",
                        "in": "path",
                        "description": "ID do autor",
                        "required": true,
                        "schema": {
                            "type": "integer"
                        }
                    }
                ],
                "requestBody": {
                    "required": true,
                    "content": {
                        "application/json": {
                            "schema": {
                                "properties": {
                                    "name": {
                                        "type": "string",
                                        "example": "Robert C. Martin"
                                    },
                                    "bio": {
                                        "type": "string",
                                        "example": "Autor de Clean Code (atualizado)"
                                    }
                                },
                                "type": "object"
                            }
                        }
                    }
                },
                "responses": {
                    "200": {
                        "description": "Autor atualizado com sucesso"
                    },
                    "404": {
                        "description": "Autor não encontrado"
                    },
                    "422": {
                        "description": "Erro de validação"
                    }
                },
                "security": [
                    {
                        "bearerAuth": []
                    }
                ]
            },
            "delete": {
                "tags": [
                    "Authors"
                ],
                "summary": "Deletar autor",
                "operationId": "ea3482a24b060fa981f9cc07c6fa92d2",
                "parameters": [
                    {
                        "name": "id",
                        "in": "path",
                        "description": "ID do autor",
                        "required": true,
                        "schema": {
                            "type": "integer"
                        }
                    }
                ],
                "responses": {
                    "204": {
                        "description": "Autor deletado com sucesso (sem conteúdo)"
                    },
                    "404": {
                        "description": "Autor não encontrado"
                    }
                },
                "security": [
                    {
                        "bearerAuth": []
                    }
                ]
            }
        },
        "/books": {
            "get": {
                "tags": [
                    "Books"
                ],
                "summary": "Listar livros",
                "operationId": "921c595372ab399821e267fcf05cbaa1",
                "parameters": [
                    {
                        "name": "per_page",
                        "in": "query",
                        "description": "Quantidade por página",
                        "required": false,
                        "schema": {
                            "type": "integer",
                            "default": 10
                        }
                    }
                ],
                "responses": {
                    "200": {
                        "description": "Lista paginada de livros"
                    },
                    "401": {
                        "description": "Não autenticado"
                    }
                },
                "security": [
                    {
                        "bearerAuth": []
                    }
                ]
            },
            "post": {
                "tags": [
                    "Books"
                ],
                "summary": "Criar livro",
                "operationId": "7ab92284110ace5d0f7de52f372e70c0",
                "requestBody": {
                    "required": true,
                    "content": {
                        "application/json": {
                            "schema": {
                                "required": [
                                    "author_id",
                                    "title"
                                ],
                                "properties": {
                                    "author_id": {
                                        "description": "ID do autor (deve existir na tabela authors)",
                                        "type": "integer",
                                        "example": 1
                                    },
                                    "title": {
                                        "type": "string",
                                        "example": "Exemplo"
                                    },
                                    "year": {
                                        "type": "string",
                                        "example": "2008"
                                    },
                                    "genre": {
                                        "type": "string",
                                        "example": "Teste"
                                    }
                                },
                                "type": "object"
                            }
                        }
                    }
                },
                "responses": {
                    "201": {
                        "description": "Livro criado com sucesso"
                    },
                    "422": {
                        "description": "Erro de validação"
                    },
                    "401": {
                        "description": "Não autenticado"
                    }
                },
                "security": [
                    {
                        "bearerAuth": []
                    }
                ]
            }
        },
        "/books/{id}": {
            "get": {
                "tags": [
                    "Books"
                ],
                "summary": "Mostrar detalhes de um livro",
                "operationId": "e079e587c1fee53fe150984526abf3ef",
                "parameters": [
                    {
                        "name": "id",
                        "in": "path",
                        "description": "ID do livro",
                        "required": true,
                        "schema": {
                            "type": "integer"
                        }
                    }
                ],
                "responses": {
                    "200": {
                        "description": "Livro encontrado"
                    },
                    "404": {
                        "description": "Livro não encontrado"
                    },
                    "401": {
                        "description": "Não autenticado"
                    }
                },
                "security": [
                    {
                        "bearerAuth": []
                    }
                ]
            },
            "put": {
                "tags": [
                    "Books"
                ],
                "summary": "Atualizar livro",
                "operationId": "b47b1606570ba86a105bf62f04de6b7f",
                "parameters": [
                    {
                        "name": "id",
                        "in": "path",
                        "description": "ID do livro",
                        "required": true,
                        "schema": {
                            "type": "integer"
                        }
                    }
                ],
                "requestBody": {
                    "required": true,
                    "content": {
                        "application/json": {
                            "schema": {
                                "properties": {
                                    "author_id": {
                                        "description": "ID do autor (opcional na atualização, mas se enviado deve existir)",
                                        "type": "integer",
                                        "example": 1
                                    },
                                    "title": {
                                        "type": "string",
                                        "example": "teste (Atualizado)"
                                    },
                                    "year": {
                                        "type": "string",
                                        "example": "2009"
                                    },
                                    "genre": {
                                        "type": "string",
                                        "example": "Software Engineering"
                                    }
                                },
                                "type": "object"
                            }
                        }
                    }
                },
                "responses": {
                    "200": {
                        "description": "Livro atualizado com sucesso"
                    },
                    "404": {
                        "description": "Livro não encontrado"
                    },
                    "422": {
                        "description": "Erro de validação"
                    },
                    "401": {
                        "description": "Não autenticado"
                    }
                },
                "security": [
                    {
                        "bearerAuth": []
                    }
                ]
            },
            "delete": {
                "tags": [
                    "Books"
                ],
                "summary": "Deletar livro",
                "operationId": "95c7fc7d78f9dc3884a5bb898b7ead11",
                "parameters": [
                    {
                        "name": "id",
                        "in": "path",
                        "description": "ID do livro",
                        "required": true,
                        "schema": {
                            "type": "integer"
                        }
                    }
                ],
                "responses": {
                    "204": {
                        "description": "Livro deletado com sucesso (sem conteúdo)"
                    },
                    "404": {
                        "description": "Livro não encontrado"
                    },
                    "401": {
                        "description": "Não autenticado"
                    }
                },
                "security": [
                    {
                        "bearerAuth": []
                    }
                ]
            }
        }
    },
    "components": {
        "securitySchemes": {
            "bearerAuth": {
                "type": "http",
                "bearerFormat": "JWT",
                "scheme": "bearer"
            }
        }
    },
    "tags": [
        {
            "name": "Auth",
            "description": "Endpoints de autenticação e recuperação de senha"
        },
        {
            "name": "Authors",
            "description": "Authors"
        },
        {
            "name": "Books",
            "description": "Books"
        }
    ]
}